Metadata-Version: 1.0
Name: dhanasak-distributions
Version: 0.1
Summary: Gaussian and Binomial distributions
Home-page: UNKNOWN
Author: Abhishek Dhanasetty
Author-email: dhanasak18@gmail.com
License: UNKNOWN
Platform: UNKNOWN
